python_llm_assistant/__init__.py
python_llm_assistant/__main__.py
python_llm_assistant/config.py
python_llm_assistant/prompts.py
python_llm_assistant-0.1.0.post0.dist-info/licenses/LICENSE
python_llm_assistant-0.1.0.post0.dist-info/METADATA
python_llm_assistant-0.1.0.post0.dist-info/WHEEL
python_llm_assistant-0.1.0.post0.dist-info/top_level.txt
python_llm_assistant-0.1.0.post0.dist-info/RECORD
