Metadata-Version: 2.4
Name: python_llm_assistant
Version: 0.1.0.post0
Summary: Telegram group chat assistant
Author: Alexandr, Vladimir, Roman
Author-email: "Alexandr, Vladimir, Roman" <roman.arzum@gmail.com>
License-File: LICENSE
Dynamic: author
Dynamic: description
Dynamic: description-content-type
Dynamic: license-file
